odoo/addons/mail_chatter_thread_colour/README.rst
odoo/addons/mail_chatter_thread_colour/__init__.py
odoo/addons/mail_chatter_thread_colour/__manifest__.py
odoo/addons/mail_chatter_thread_colour/data/ir_config_parameter_data.xml
odoo/addons/mail_chatter_thread_colour/demo/ir_model.xml
odoo/addons/mail_chatter_thread_colour/i18n/mail_chatter_thread_colour.pot
odoo/addons/mail_chatter_thread_colour/models/__init__.py
odoo/addons/mail_chatter_thread_colour/models/assetsbundle.py
odoo/addons/mail_chatter_thread_colour/models/ir_model.py
odoo/addons/mail_chatter_thread_colour/models/ir_qweb.py
odoo/addons/mail_chatter_thread_colour/models/res_config_settings.py
odoo/addons/mail_chatter_thread_colour/readme/CONFIGURE.rst
odoo/addons/mail_chatter_thread_colour/readme/CONTRIBUTORS.rst
odoo/addons/mail_chatter_thread_colour/readme/DESCRIPTION.rst
odoo/addons/mail_chatter_thread_colour/static/description/icon.png
odoo/addons/mail_chatter_thread_colour/static/description/index.html
odoo/addons/mail_chatter_thread_colour/static/src/xml/thread.xml
odoo/addons/mail_chatter_thread_colour/templates/assets.xml
odoo/addons/mail_chatter_thread_colour/views/ir_model.xml
odoo/addons/mail_chatter_thread_colour/views/res_config_settings.xml
odoo14_addon_mail_chatter_thread_colour-14.0.1.0.1.dist-info/METADATA
odoo14_addon_mail_chatter_thread_colour-14.0.1.0.1.dist-info/WHEEL
odoo14_addon_mail_chatter_thread_colour-14.0.1.0.1.dist-info/top_level.txt
odoo14_addon_mail_chatter_thread_colour-14.0.1.0.1.dist-info/RECORD
